lmsi/__init__.py
lmsi/cli.py
lmsi/container.py
lmsi/core.py
lmsi/templates/base.html
lmsi/templates/mathjax.js
lmsi/templates/plot_viewer.html
lmsi/templates/polyfill.js
lmsi/templates/style.css
lmsi/webpage/__init__.py
lmsi/webpage/html.py
let_me_scroll_it-0.0.5.dist-info/LICENSE
let_me_scroll_it-0.0.5.dist-info/METADATA
let_me_scroll_it-0.0.5.dist-info/WHEEL
let_me_scroll_it-0.0.5.dist-info/entry_points.txt
let_me_scroll_it-0.0.5.dist-info/top_level.txt
let_me_scroll_it-0.0.5.dist-info/RECORD
