Metadata-Version: 2.1
Name: let-me-scroll-it
Version: 0.0.5
Summary: A command-line utility for placing figures in a static webpage
Author-email: Josh Borrow <josh@joshborrow.com>
Requires-Python: >=3.10
License-File: LICENSE
Requires-Dist: jinja2
Requires-Dist: unyt
Requires-Dist: pydantic
